MANIFEST.in
README.md
requirements.txt
setup.cfg
setup.py
bin/test-templates.py
yodeploy/__init__.py
yodeploy/__main__.py
yodeploy/application.py
yodeploy/config.py
yodeploy/deploy.py
yodeploy/ipc_logging.py
yodeploy/locking.py
yodeploy/repository.py
yodeploy/unicode_stdout.py
yodeploy/util.py
yodeploy/virtualenv.py
yodeploy.egg-info/PKG-INFO
yodeploy.egg-info/SOURCES.txt
yodeploy.egg-info/dependency_links.txt
yodeploy.egg-info/requires.txt
yodeploy.egg-info/top_level.txt
yodeploy/cmds/__init__.py
yodeploy/cmds/build_artifact.py
yodeploy/cmds/build_virtualenv.py
yodeploy/cmds/deploy.py
yodeploy/cmds/spade.py
yodeploy/cmds/yodeploy_server.py
yodeploy/cmds/tests/__init__.py
yodeploy/cmds/tests/test_build_artifact.py
yodeploy/cmds/tests/test_build_virtualenv.py
yodeploy/cmds/tests/test_deploy.py
yodeploy/cmds/tests/test_spade.py
yodeploy/flask_app/__init__.py
yodeploy/flask_app/app.py
yodeploy/flask_app/auth.py
yodeploy/flask_app/errors.py
yodeploy/flask_app/views.py
yodeploy/hooks/__init__.py
yodeploy/hooks/apache.py
yodeploy/hooks/base.py
yodeploy/hooks/configurator.py
yodeploy/hooks/daemon.py
yodeploy/hooks/data.py
yodeploy/hooks/django.py
yodeploy/hooks/htpasswd.py
yodeploy/hooks/nginx.py
yodeploy/hooks/python.py
yodeploy/hooks/templating.py
yodeploy/hooks/tomcat.py
yodeploy/hooks/tests/__init__.py
yodeploy/hooks/tests/test_base.py
yodeploy/hooks/tests/test_configurator.py
yodeploy/hooks/tests/test_django.py
yodeploy/hooks/tests/test_htpasswd.py
yodeploy/hooks/tests/test_nginx.py
yodeploy/hooks/tests/test_python.py
yodeploy/hooks/tests/test_templating.py
yodeploy/test_integration/__init__.py
yodeploy/test_integration/deployconf.py
yodeploy/test_integration/helpers.py
yodeploy/test_integration/test__main__.py
yodeploy/test_integration/test_apache_hooks.py
yodeploy/test_integration/test_basic_app.py
yodeploy/test_integration/test_buildvirtualenv.py
yodeploy/test_integration/test_config_template.py
yodeploy/test_integration/test_django_hooks.py
yodeploy/test_integration/test_nginx_hooks.py
yodeploy/test_integration/test_server.py
yodeploy/test_integration/testcase.py
yodeploy/test_integration/samples/__init__.py
