Metadata-Version: 1.0
Name: yodeploy
Version: 0.10.3
Summary: Helpers for Deploy hooks
Home-page: https://kaiam-ci.pcnt.io/simple/yodeploy
Author: Roxana Debenedetti
Author-email: roxana.debenedetti@poincenot.com
License: UNKNOWN
Platform: UNKNOWN
